docs/source/conf.py
shift/__init__.py
shift/cart/__init__.py
shift/cart/conv.py
shift/cart/diff.py
shift/cart/fft.py
shift/cart/grid.py
shift/cart/kgrid.py
shift/cart/mpi_fft.py
shift/cart/mpi_grid.py
shift/cart/mpi_kgrid.py
shift/cart/mpi_pofk.py
shift/cart/multiply.py
shift/cart/pofk.py
shift/cart/utils.py
shift/mpiutils/__init__.py
shift/mpiutils/loops.py
shift/mpiutils/mpiclass.py
shift/polar/__init__.py
shift/polar/bessel.py
shift/polar/grid.py
shift/polar/pft.py
shift/polar/pft_basis.py
shift/sphere/__init__.py
shift/sphere/grid.py
shift/sphere/sbt.py
shift/sphere/sht.py
shift/src/__init__.py
shift/src/bin.py
shift/src/pft.py
shift/utils/__init__.py
shift/utils/progress.py
tests/mpi_tests/__init__.py
tests/mpi_tests/test_mpi_fft.py
tests/mpi_tests/test_mpi_grid.py
tests/mpi_tests/test_mpi_kgrid.py
tests/mpi_tests/test_mpiutils_mpiclass.py
tests/normal_tests/__init__.py
tests/normal_tests/test_cart_conv.py
tests/normal_tests/test_cart_diff.py
tests/normal_tests/test_cart_fft.py
tests/normal_tests/test_cart_grid.py
tests/normal_tests/test_cart_kgrid.py
tests/normal_tests/test_cart_mpi_fft.py
tests/normal_tests/test_cart_multiply.py
tests/normal_tests/test_cart_pofk.py
tests/normal_tests/test_cart_utils.py
tests/normal_tests/test_mpiutils_loops.py
tests/normal_tests/test_src_bin.py
tests/normal_tests/test_utils_progress.py
shift_fft-1.0.4.dist-info/METADATA
shift_fft-1.0.4.dist-info/WHEEL
shift_fft-1.0.4.dist-info/top_level.txt
shift_fft-1.0.4.dist-info/RECORD
