Metadata-Version: 2.4
Name: shift-fft
Version: 1.0.4
Summary: SHIFT is a scalable MPI library for computing fast Fourier transforms in python.
Author-email: Krishna Naidoo <krishna.naidoo.11@ucl.ac.uk>
Maintainer-email: Krishna Naidoo <krishna.naidoo.11@ucl.ac.uk>
Project-URL: Homepage, https://github.com/knaidoo29/SHIFT
Project-URL: Repository, https://github.com/knaidoo29/SHIFT
Project-URL: Documentation, https://shift-doc.readthedocs.io/en/latest/
Project-URL: Bug Tracker, https://github.com/knaidoo29/SHIFT/issues
Project-URL: Changelog, https://github.com/knaidoo29/SHIFT/blob/main/CHANGELOG.md
Keywords: mathematics,fourier transforms
Classifier: Development Status :: 5 - Production/Stable
Classifier: Intended Audience :: Developers
Classifier: Intended Audience :: Science/Research
Classifier: Natural Language :: English
Classifier: Programming Language :: Python :: 3
Classifier: Programming Language :: Python :: 3.8
Classifier: Programming Language :: Python :: 3.9
Classifier: Programming Language :: Python :: 3.10
Classifier: Programming Language :: Python :: 3.11
Classifier: Programming Language :: Python :: 3.12
Classifier: Topic :: Scientific/Engineering
Classifier: Topic :: Scientific/Engineering :: Mathematics
Requires-Dist: numba
Requires-Dist: numpy
Requires-Dist: scipy
Provides-Extra: dev
Requires-Dist: black; extra == "dev"
Requires-Dist: flake8; extra == "dev"
Requires-Dist: ipython; extra == "dev"
Requires-Dist: jupyter; extra == "dev"
Requires-Dist: mypy; extra == "dev"
Provides-Extra: docs
Requires-Dist: numpydoc; extra == "docs"
Requires-Dist: sphinx; extra == "docs"
Requires-Dist: sphinx-rtd-theme; extra == "docs"
Provides-Extra: test
Requires-Dist: pytest>=6.0; extra == "test"
Requires-Dist: pytest-cov; extra == "test"
